pro_website_maker/__init__.py
pro_website_maker/main.py
pro_website_maker/module_loader.py
pro_website_maker/output_file.py
pro_website_maker/modules/contact/__init__.py
pro_website_maker/modules/github_pages/__init__.py
pro_website_maker/modules/markdown/__init__.py
pro_website_maker/modules/resume/__init__.py
pro_website_maker/modules/sitemap/__init__.py
pro_website_maker/modules/static/__init__.py
pro_website_maker/templates/base.html
pro_website_maker/templates/markdown.html
pro_website_maker/templates/resume.html
pro_website_maker/templates/sitemap.xml
pro_website_maker/templates/Contact/Form.html
pro_website_maker/templates/Contact/Sent.html
pro_website_maker-0.5.2.dist-info/METADATA
pro_website_maker-0.5.2.dist-info/WHEEL
pro_website_maker-0.5.2.dist-info/entry_points.txt
pro_website_maker-0.5.2.dist-info/licenses/LICENSE
pro_website_maker-0.5.2.dist-info/RECORD
