Metadata-Version: 2.3
Name: pro-website-maker
Version: 0.5.2
Summary: A command-line interface tool to make a professional HTML website from YAML files.
Project-URL: Homepage, https://github.com/d3987ef8/pwm
Project-URL: Issues, https://github.com/d3987ef8/pwm/issues
Author-email: Jack Murray <info@jackmurray.com>
License-File: LICENSE
Classifier: License :: OSI Approved :: MIT License
Classifier: Operating System :: OS Independent
Classifier: Programming Language :: Python :: 3
Requires-Python: >=3.9
Requires-Dist: jinja2
Requires-Dist: markdown
Requires-Dist: pyyaml
